odoo/addons/helpdesk_mgmt_rating/README.rst
odoo/addons/helpdesk_mgmt_rating/__init__.py
odoo/addons/helpdesk_mgmt_rating/__manifest__.py
odoo/addons/helpdesk_mgmt_rating/data/helpdesk_data.xml
odoo/addons/helpdesk_mgmt_rating/i18n/ca.po
odoo/addons/helpdesk_mgmt_rating/i18n/helpdesk_mgmt_rating.pot
odoo/addons/helpdesk_mgmt_rating/models/__init__.py
odoo/addons/helpdesk_mgmt_rating/models/helpdesk_ticket.py
odoo/addons/helpdesk_mgmt_rating/models/helpdesk_ticket_stage.py
odoo/addons/helpdesk_mgmt_rating/readme/CONFIGURE.rst
odoo/addons/helpdesk_mgmt_rating/readme/CONTRIBUTORS.rst
odoo/addons/helpdesk_mgmt_rating/readme/DESCRIPTION.rst
odoo/addons/helpdesk_mgmt_rating/static/description/icon.png
odoo/addons/helpdesk_mgmt_rating/static/description/index.html
odoo/addons/helpdesk_mgmt_rating/views/helpdesk_ticket_menu.xml
odoo/addons/helpdesk_mgmt_rating/views/helpdesk_ticket_stage_view.xml
odoo/addons/helpdesk_mgmt_rating/views/helpdesk_ticket_view.xml
odoo11_addon_helpdesk_mgmt_rating-11.0.1.0.0.99.dev10.dist-info/METADATA
odoo11_addon_helpdesk_mgmt_rating-11.0.1.0.0.99.dev10.dist-info/WHEEL
odoo11_addon_helpdesk_mgmt_rating-11.0.1.0.0.99.dev10.dist-info/top_level.txt
odoo11_addon_helpdesk_mgmt_rating-11.0.1.0.0.99.dev10.dist-info/RECORD
